csvgather/__init__.py
csvgather/csvgather.py
csvgather-1.1.1.dist-info/DESCRIPTION.rst
csvgather-1.1.1.dist-info/METADATA
csvgather-1.1.1.dist-info/RECORD
csvgather-1.1.1.dist-info/WHEEL
csvgather-1.1.1.dist-info/entry_points.txt
csvgather-1.1.1.dist-info/metadata.json
csvgather-1.1.1.dist-info/top_level.txt
