Metadata-Version: 2.0
Name: csvgather
Version: 1.1.1
Summary: A tool for collecting sets of character separated value files and joining into a single matrix file with column selection and column name manipulation operations
Home-page: https://bitbucket.org/adamlabadorf/csvgather/overview
Author: Adam Labadorf
Author-email: alabadorf@gmail.com
License: MIT
Platform: UNKNOWN
Classifier: Development Status :: 5 - Production/Stable
Classifier: Intended Audience :: Science/Research
Classifier: Intended Audience :: Information Technology
Classifier: Intended Audience :: System Administrators
Classifier: Topic :: Utilities
Classifier: License :: OSI Approved :: MIT License
Classifier: Programming Language :: Python :: 3
Classifier: Programming Language :: Python :: 3.2
Classifier: Programming Language :: Python :: 3.3
Classifier: Programming Language :: Python :: 3.4
Classifier: Environment :: Console
Requires-Python: >= 3
Requires-Dist: docopt
Requires-Dist: pandas (>=0.21.0)
